{
  "updated_at": "2026-05-11T06:00:07.854684+00:00",
  "capital": {
    "balance": 10.0,
    "initial": 10.0,
    "pnl": 0.0,
    "return_pct": 0.0,
    "in_trade": true,
    "total_trades": 0,
    "win_rate": 0,
    "current_trade": {
      "pair": "ETH",
      "entry_price": 2321.42,
      "entry_time": "2026-05-10T12:12:47.963946+00:00",
      "amount_usd": 10.0
    }
  },
  "prices": {
    "BTC": {
      "usd": 80810,
      "change": 0.15148518866813385
    },
    "ETH": {
      "usd": 2335.01,
      "change": 0.34324749337379223
    },
    "SOL": {
      "usd": 95.67,
      "change": 2.495003421622226
    }
  },
  "signals": [
    {
      "pair": "BTC",
      "action": "BUY",
      "price": 80810
    },
    {
      "pair": "ETH",
      "action": "BUY",
      "price": 2335.01
    },
    {
      "pair": "SOL",
      "action": "NEUTRAL",
      "price": 95.67
    }
  ],
  "aud_usd": 0.7229999267982998
}